CHANGES
LICENSE
MANIFEST.in
README
setup.py
zonecreate/__init__.py
zonecreate/zone_add_record.py
zonecreate/zone_create.py
zonecreate/zone_del_record.py
zonecreate/zone_refresh.py
zonecreate/zone_update_soa.py
zonecreate.egg-info/PKG-INFO
zonecreate.egg-info/SOURCES.txt
zonecreate.egg-info/dependency_links.txt
zonecreate.egg-info/entry_points.txt
zonecreate.egg-info/not-zip-safe
zonecreate.egg-info/requires.txt
zonecreate.egg-info/top_level.txt
zonecreate/templates/A.template
zonecreate/templates/GENERIC.template
zonecreate/templates/MX.template
zonecreate/templates/NS.template
zonecreate/templates/SOA.template