Metadata-Version: 1.0
Name: zonecreate
Version: 0.1
Summary: zonecreate are some helper scripts for generating zone files
Home-page: https://github.com/bertjwregeer/zonecreate
Author: Bert JW Regeer
Author-email: bertjw@regeer.org
License: UNKNOWN
Keywords: dns zones
Platform: UNKNOWN
Classifier: Programming Language :: Python
Classifier: Development Status :: 2 - Pre-Alpha
Classifier: Topic :: Internet :: Name Service (DNS)
Classifier: Topic :: Utilities
Classifier: Programming Language :: Python :: 2
Classifier: Programming Language :: Python :: 2.7
Classifier: Operating System :: Unix
Classifier: License :: OSI Approved :: BSD License
Classifier: Intended Audience :: System Administrators
